[
  {
    "name": "25_RWY",
    "lat": 33.514036,
    "lon": 126.493535,
    "alt": 300,
    "wspd": 40,
    "wdir": 90
  },
  {
    "name": "25_RWY",
    "lat": 33.514036,
    "lon": 126.493535,
    "alt": 600,
    "wspd": 40,
    "wdir": 90
  },
  {
    "name": "25_RWY",
    "lat": 33.514036,
    "lon": 126.493535,
    "alt": 900,
    "wspd": 40,
    "wdir": 90
  },
  {
    "name": "25_RWY",
    "lat": 33.514036,
    "lon": 126.493535,
    "alt": 1200,
    "wspd": 40,
    "wdir": 90
  },
  {
    "name": "25_RWY",
    "lat": 33.514036,
    "lon": 126.493535,
    "alt": 1500,
    "wspd": 40,
    "wdir": 90
  },
  {
    "name": "25_1NM",
    "lat": 33.514036,
    "lon": 126.513524,
    "alt": 300,
    "wspd": 40,
    "wdir": 90
  },
  {
    "name": "25_1NM",
    "lat": 33.514036,
    "lon": 126.513524,
    "alt": 600,
    "wspd": 40,
    "wdir": 90
  },
  {
    "name": "25_1NM",
    "lat": 33.514036,
    "lon": 126.513524,
    "alt": 900,
    "wspd": 40,
    "wdir": 90
  },
  {
    "name": "25_1NM",
    "lat": 33.514036,
    "lon": 126.513524,
    "alt": 1200,
    "wspd": 40,
    "wdir": 90
  },
  {
    "name": "25_1NM",
    "lat": 33.514036,
    "lon": 126.513524,
    "alt": 1500,
    "wspd": 40,
    "wdir": 90
  },
  {
    "name": "25_2NM",
    "lat": 33.514036,
    "lon": 126.533513,
    "alt": 300,
    "wspd": 40,
    "wdir": 90
  },
  {
    "name": "25_2NM",
    "lat": 33.514036,
    "lon": 126.533513,
    "alt": 600,
    "wspd": 40,
    "wdir": 90
  },
  {
    "name": "25_2NM",
    "lat": 33.514036,
    "lon": 126.533513,
    "alt": 900,
    "wspd": 40,
    "wdir": 90
  },
  {
    "name": "25_2NM",
    "lat": 33.514036,
    "lon": 126.533513,
    "alt": 1200,
    "wspd": 40,
    "wdir": 90
  },
  {
    "name": "25_2NM",
    "lat": 33.514036,
    "lon": 126.533513,
    "alt": 1500,
    "wspd": 40,
    "wdir": 90
  },
  {
    "name": "25_3NM",
    "lat": 33.514036,
    "lon": 126.553502,
    "alt": 300,
    "wspd": 40,
    "wdir": 90
  },
  {
    "name": "25_4NM",
    "lat": 33.514036,
    "lon": 126.573491,
    "alt": 300,
    "wspd": 40,
    "wdir": 90
  },
  {
    "name": "25_5NM",
    "lat": 33.514036,
    "lon": 126.593480,
    "alt": 300,
    "wspd": 40,
    "wdir": 90
  },
  {
    "name": "07_RWY",
    "lat": 33.502692,
    "lon": 126.471227,
    "alt": 300,
    "wspd": 40,
    "wdir": 90
  },
  {
    "name": "07_1NM",
    "lat": 33.502692,
    "lon": 126.451245,
    "alt": 300,
    "wspd": 40,
    "wdir": 90
  },
  {
    "name": "07_2NM",
    "lat": 33.502692,
    "lon": 126.431263,
    "alt": 300,
    "wspd": 40,
    "wdir": 90
  },
  {
    "name": "07_3NM",
    "lat": 33.502692,
    "lon": 126.411281,
    "alt": 300,
    "wspd": 40,
    "wdir": 90
  },
  {
    "name": "07_4NM",
    "lat": 33.502692,
    "lon": 126.391299,
    "alt": 300,
    "wspd": 40,
    "wdir": 90
  },
  {
    "name": "07_5NM",
    "lat": 33.502692,
    "lon": 126.371317,
    "alt": 300,
    "wspd": 40,
    "wdir": 90
  }
]